henotace_ai/__init__.py
henotace_ai/index.py
henotace_ai/logger.py
henotace_ai/tutor.py
henotace_ai/types.py
henotace_ai/connectors/__init__.py
henotace_ai/connectors/inmemory.py
henotace_ai_sdk-1.2.0.dist-info/METADATA
henotace_ai_sdk-1.2.0.dist-info/WHEEL
henotace_ai_sdk-1.2.0.dist-info/entry_points.txt
henotace_ai_sdk-1.2.0.dist-info/top_level.txt
henotace_ai_sdk-1.2.0.dist-info/RECORD
